{"proved": true, "proof_script": "lemma OclIncludes_valid_args_valid''[simp,code_unfold]: \"\\<upsilon>(X->includes\\<^sub>B\\<^sub>a\\<^sub>g(x)) = ((\\<delta> X) and (\\<upsilon> x))\"\nby (simp add: OclIncludes.def_valid_then_def)", "proof_length": 1, "agent_info": {"prediction_time": 2.051804304122925, "isabelle_time": 0.039823055267333984, "problem_loading_time": 3.8830742835998535, "proof_length": 1, "successful_proof": "lemma OclIncludes_valid_args_valid''[simp,code_unfold]: \"\\<upsilon>(X->includes\\<^sub>B\\<^sub>a\\<^sub>g(x)) = ((\\<delta> X) and (\\<upsilon> x))\"\nby (simp add: OclIncludes.def_valid_then_def)", "result": "proved"}}