{"proved": true, "proof_script": "lemma val2formOfSingleLiteralValuation: assumes \"length v = 1\" shows \"val2form v = [[hd v]]\"\nusing assms\nby(induct v,auto)", "proof_length": 2, "agent_info": {"prediction_time": 3.60573148727417, "isabelle_time": 0.524381160736084, "problem_loading_time": 2.828470230102539, "proof_length": 2, "successful_proof": "lemma val2formOfSingleLiteralValuation: assumes \"length v = 1\" shows \"val2form v = [[hd v]]\"\nusing assms\nby(induct v,auto)", "result": "proved"}}