{"proved": true, "proof_script": "lemma Im2_divide_numeral [simp]: \"Im2 (x / numeral w) = Im2 x / numeral w\"\nunfolding Im2_def\napply (simp add: quat_divide_numeral semiring_normalization_rules(29))\napply (cases x)\napply simp\napply transfer\nby (simp add: scaleR_quat.code)", "proof_length": 6, "agent_info": {"prediction_time": 25.888196229934692, "isabelle_time": 86.1463782787323, "problem_loading_time": 4.778718948364258, "proof_length": 6, "successful_proof": "lemma Im2_divide_numeral [simp]: \"Im2 (x / numeral w) = Im2 x / numeral w\"\nunfolding Im2_def\napply (simp add: quat_divide_numeral semiring_normalization_rules(29))\napply (cases x)\napply simp\napply transfer\nby (simp add: scaleR_quat.code)", "result": "proved"}}