{"proved": true, "proof_script": "lemma is_process8: \"is_process P \\<Longrightarrow> \\<forall> s X. s \\<notin> DIVERGENCES P \\<or> (s,X) \\<in> FAILURES P\"\nby(drule is_process_spec[THEN iffD1], metis)", "proof_length": 1, "agent_info": {"prediction_time": 1.9625663757324219, "isabelle_time": 0.09713578224182129, "problem_loading_time": 2.2120163440704346, "proof_length": 1, "successful_proof": "lemma is_process8: \"is_process P \\<Longrightarrow> \\<forall> s X. s \\<notin> DIVERGENCES P \\<or> (s,X) \\<in> FAILURES P\"\nby(drule is_process_spec[THEN iffD1], metis)", "result": "proved"}}