{"proved": true, "proof_script": "lemma invar_rev[simp]: \"queue_invar (rev q) \\<longleftrightarrow> queue_invar q\"\nby (case_tac q) (auto simp add: queue_invar_def)", "proof_length": 1, "agent_info": {"prediction_time": 1.994645357131958, "isabelle_time": 0.10515713691711426, "problem_loading_time": 9.38103699684143, "proof_length": 1, "successful_proof": "lemma invar_rev[simp]: \"queue_invar (rev q) \\<longleftrightarrow> queue_invar q\"\nby (case_tac q) (auto simp add: queue_invar_def)", "result": "proved"}}