{"proved": true, "proof_script": "lemma silent_move_iff: \"silent_move = (\\<lambda>s s'. (\\<exists>tl. trsys s tl s' \\<and> \\<tau>move s tl s'))\"\nby(auto simp add: fun_eq_iff)", "proof_length": 1, "agent_info": {"prediction_time": 1.8343861103057861, "isabelle_time": 0.15494084358215332, "problem_loading_time": 2.128777503967285, "proof_length": 1, "successful_proof": "lemma silent_move_iff: \"silent_move = (\\<lambda>s s'. (\\<exists>tl. trsys s tl s' \\<and> \\<tau>move s tl s'))\"\nby(auto simp add: fun_eq_iff)", "result": "proved"}}